asyncjisho/__init__.py
asyncjisho/jisho.py
asyncjisho-0.2.0.dist-info/DESCRIPTION.rst
asyncjisho-0.2.0.dist-info/METADATA
asyncjisho-0.2.0.dist-info/RECORD
asyncjisho-0.2.0.dist-info/WHEEL
asyncjisho-0.2.0.dist-info/metadata.json
asyncjisho-0.2.0.dist-info/top_level.txt
